kerasGPTcopilot/__init__.py
kerasGPTcopilot/core/ModelAdvisor.py
kerasGPTcopilot/core/__init__.py
kerasGPTcopilot/extras/__init__.py
kerasGPTcopilot/extras/util.py
keras_gpt_copilot-0.1.4.dist-info/LICENSE
keras_gpt_copilot-0.1.4.dist-info/METADATA
keras_gpt_copilot-0.1.4.dist-info/WHEEL
keras_gpt_copilot-0.1.4.dist-info/top_level.txt
keras_gpt_copilot-0.1.4.dist-info/RECORD
